sqlninja/__init__.py
sqlninja/engine.py
sqlninja/main.py
sqlninja/utils.py
sql_ninja-0.2.1.dist-info/LICENSE
sql_ninja-0.2.1.dist-info/METADATA
sql_ninja-0.2.1.dist-info/WHEEL
sql_ninja-0.2.1.dist-info/entry_points.txt
sql_ninja-0.2.1.dist-info/top_level.txt
sql_ninja-0.2.1.dist-info/RECORD
