Metadata-Version: 2.1
Name: sql-ninja
Version: 0.2.1
Summary: SQL + Jinja Templates Done Right™
Home-page: https://github.com/ddrscott/sql-ninja
Author: Scott Pierce
Author-email: ddrscott@gmail.com
License: UNKNOWN
Platform: UNKNOWN
Classifier: Programming Language :: Python :: 3
Classifier: License :: OSI Approved :: MIT License
Classifier: Operating System :: OS Independent
Requires-Python: >=3.6
Requires-Dist: click
Requires-Dist: jinja2
